fixtures_git/__init__.py
fixtures_git/gitfixture.py
fixtures_git/utils.py
fixtures_git-0.1.0.dist-info/METADATA
fixtures_git-0.1.0.dist-info/RECORD
fixtures_git-0.1.0.dist-info/WHEEL
fixtures_git-0.1.0.dist-info/pbr.json
fixtures_git-0.1.0.dist-info/top_level.txt
